{"100121":{"value_list":[{"multi_lang":[{"value":"1 Month","language":"en"},{"value":"1 Bulan","language":"id"}],"value_id":776,"value_type":3,"children":[],"display_name":"1 Bulan"},{"multi_lang":[{"value":"12 Months","language":"en"},{"value":"12 Bulan","language":"id"}],"value_id":822,"value_type":3,"children":[],"display_name":"12 Bulan"},{"multi_lang":[{"value":"2 Months","language":"en"},{"value":"2 Bulan","language":"id"}],"value_id":789,"value_type":3,"children":[],"display_name":"2 Bulan"},{"multi_lang":[{"value":"24 Months","language":"en"},{"value":"24 Bulan","language":"id"}],"value_id":831,"value_type":3,"children":[],"display_name":"24 Bulan"},{"multi_lang":[{"value":"3 Months","language":"en"},{"value":"3 Bulan","language":"id"}],"value_id":799,"value_type":3,"children":[],"display_name":"3 Bulan"},{"multi_lang":[{"value":"3 Years","language":"en"},{"value":"3 Tahun","language":"id"}],"value_id":857,"value_type":3,"children":[],"display_name":"3 Tahun"},{"multi_lang":[{"value":"5 Years","language":"en"},{"value":"5 Tahun","language":"id"}],"value_id":843,"value_type":3,"children":[],"display_name":"5 Tahun"},{"multi_lang":[{"value":"6 Months","language":"en"},{"value":"6 Bulan","language":"id"}],"value_id":810,"value_type":3,"children":[],"display_name":"6 Bulan"}],"name":"Masa Garansi"},"100134":{"value_list":[{"multi_lang":[{"value":"Canvas","language":"en"},{"value":"Kanvas","language":"id"}],"value_id":1129,"value_type":3,"children":[],"display_name":"Kanvas"},{"multi_lang":[{"value":"Cotton","language":"en"},{"value":"Katun","language":"id"}],"value_id":1149,"value_type":3,"children":[],"display_name":"Katun"},{"multi_lang":[{"value":"Fabric","language":"en"},{"value":"Kain","language":"id"}],"value_id":1209,"value_type":3,"children":[],"display_name":"Kain"},{"multi_lang":[{"value":"Leather","language":"en"},{"value":"Kulit","language":"id"}],"value_id":1221,"value_type":3,"children":[],"display_name":"Kulit"},{"multi_lang":[{"value":"Metal","language":"en"},{"value":"Logam","language":"id"}],"value_id":1223,"value_type":3,"children":[],"display_name":"Logam"},{"multi_lang":[{"value":"Neoprene","language":"en"},{"value":"Neoprene","language":"id"}],"value_id":1726,"value_type":3,"children":[],"display_name":"Neoprene"},{"multi_lang":[{"value":"Others","language":"en"},{"value":"Lainnya","language":"id"}],"value_id":1257,"value_type":3,"children":[],"display_name":"Lainnya"},{"multi_lang":[{"value":"Plastic","language":"en"},{"value":"Plastik","language":"id"}],"value_id":1207,"value_type":3,"children":[],"display_name":"Plastik"},{"multi_lang":[{"value":"Rubber","language":"en"},{"value":"Karet","language":"id"}],"value_id":1190,"value_type":3,"children":[],"display_name":"Karet"},{"multi_lang":[{"value":"Sheepskin","language":"en"},{"value":"nan","language":"id"}],"value_id":2100,"value_type":3,"children":[],"display_name":"nan"},{"multi_lang":[{"value":"Vinyl","language":"en"},{"value":"Vinil","language":"id"}],"value_id":1981,"value_type":3,"children":[],"display_name":"Vinil"}],"name":"Bahan"},"100211":{"value_list":[{"multi_lang":[{"value":"24 Hours Recording","language":"en"},{"value":"Rekaman 24 Jam","language":"id"}],"value_id":1859,"value_type":3,"children":[],"display_name":"Rekaman 24 Jam"},{"multi_lang":[{"value":"Loop Recording","language":"en"},{"value":"Perekaman Loop","language":"id"}],"value_id":1871,"value_type":3,"children":[],"display_name":"Perekaman Loop"},{"multi_lang":[{"value":"Photo Mode","language":"en"},{"value":"Mode Foto","language":"id"}],"value_id":1883,"value_type":3,"children":[],"display_name":"Mode Foto"},{"multi_lang":[{"value":"Speed Camera Alerts","language":"en"},{"value":"Peringatan Kamera Kecepatan","language":"id"}],"value_id":1892,"value_type":3,"children":[],"display_name":"Peringatan Kamera Kecepatan"},{"multi_lang":[{"value":"WIFI-Enabled","language":"en"},{"value":"Jaringan WiFi","language":"id"}],"value_id":1909,"value_type":3,"children":[],"display_name":"Jaringan WiFi"}],"name":"Fitur"},"100370":{"value_list":[{"multi_lang":[{"value":"Supplier Warranty","language":"en"},{"value":"Garansi Supplier","language":"id"}],"value_id":2437,"value_type":3,"children":[],"display_name":"Garansi Supplier"},{"multi_lang":[{"value":"Manufacturer Warranty","language":"en"},{"value":"Garansi Produsen","language":"id"}],"value_id":2419,"value_type":3,"children":[],"display_name":"Garansi Produsen"},{"multi_lang":[{"value":"International Warranty","language":"en"},{"value":"Garansi Internasional","language":"id"}],"value_id":2397,"value_type":3,"children":[],"display_name":"Garansi Internasional"}],"name":"Jenis Garansi"},"100403":{"value_list":[{"multi_lang":[{"value":"24fps","language":"en"},{"value":"24fps","language":"id"}],"value_id":4869,"value_type":3,"children":[],"display_name":"24fps"},{"multi_lang":[{"value":"30fps","language":"en"},{"value":"30fps","language":"id"}],"value_id":4852,"value_type":3,"children":[],"display_name":"30fps"},{"multi_lang":[{"value":"60fps","language":"en"},{"value":"60fps","language":"id"}],"value_id":4889,"value_type":3,"children":[],"display_name":"60fps"}],"name":"Frame Rate"},"100569":{"value_list":[{"multi_lang":[{"value":"360p","language":"en"},{"value":"360p","language":"id"}],"value_id":3123,"value_type":3,"children":[],"display_name":"360p"},{"multi_lang":[{"value":"480p","language":"en"},{"value":"480p","language":"id"}],"value_id":3136,"value_type":3,"children":[],"display_name":"480p"},{"multi_lang":[{"value":"720p","language":"en"},{"value":"720p","language":"id"}],"value_id":3168,"value_type":3,"children":[],"display_name":"720p"},{"multi_lang":[{"value":"1080p","language":"en"},{"value":"1080p","language":"id"}],"value_id":3153,"value_type":3,"children":[],"display_name":"1080p"},{"multi_lang":[{"value":"1440p","language":"en"},{"value":"1440p","language":"id"}],"value_id":3181,"value_type":3,"children":[],"display_name":"1440p"},{"multi_lang":[{"value":"4K","language":"en"},{"value":"4K","language":"id"}],"value_id":3190,"value_type":3,"children":[],"display_name":"4K"},{"multi_lang":[{"value":"960p","language":"en"},{"value":"960p","language":"id"}],"value_id":3210,"value_type":3,"children":[],"display_name":"960p"}],"name":"Resolusi Pengambilan Video"},"100866":{"value_list":[],"name":"Model yang Sesuai"},"100879":{"value_list":[{"multi_lang":[{"value":"1GB","language":"en"},{"value":"1GB","language":"id"}],"value_id":5421,"value_type":3,"children":[],"display_name":"1GB"},{"multi_lang":[{"value":"2GB","language":"en"},{"value":"2GB","language":"id"}],"value_id":5422,"value_type":3,"children":[],"display_name":"2GB"}],"name":"Ukuran Memori"},"100911":{"value_list":[{"multi_lang":[{"value":"Front","language":"en"},{"value":"Depan","language":"id"}],"value_id":4593,"value_type":3,"children":[],"display_name":"Depan"},{"multi_lang":[{"value":"Front and Rear Set","language":"en"},{"value":"Set Depan & Belakang","language":"id"}],"value_id":4633,"value_type":3,"children":[],"display_name":"Set Depan & Belakang"},{"multi_lang":[{"value":"Full set","language":"en"},{"value":"Set Lengkap","language":"id"}],"value_id":4650,"value_type":3,"children":[],"display_name":"Set Lengkap"},{"multi_lang":[{"value":"Rear","language":"en"},{"value":"Belakang","language":"id"}],"value_id":4667,"value_type":3,"children":[],"display_name":"Belakang"}],"name":"Posisi"},"100967":{"value_list":[],"name":"TIS No."},"100969":{"value_list":[],"name":"BSMI"},"100970":{"value_list":[],"name":"NCC"}}