{"100121":{"value_list":[{"multi_lang":[{"value":"1 Month","language":"en"},{"value":"1 Bulan","language":"id"}],"value_id":776,"value_type":3,"children":[],"display_name":"1 Bulan"},{"multi_lang":[{"value":"12 Months","language":"en"},{"value":"12 Bulan","language":"id"}],"value_id":822,"value_type":3,"children":[],"display_name":"12 Bulan"},{"multi_lang":[{"value":"2 Months","language":"en"},{"value":"2 Bulan","language":"id"}],"value_id":789,"value_type":3,"children":[],"display_name":"2 Bulan"},{"multi_lang":[{"value":"24 Months","language":"en"},{"value":"24 Bulan","language":"id"}],"value_id":831,"value_type":3,"children":[],"display_name":"24 Bulan"},{"multi_lang":[{"value":"3 Months","language":"en"},{"value":"3 Bulan","language":"id"}],"value_id":799,"value_type":3,"children":[],"display_name":"3 Bulan"},{"multi_lang":[{"value":"3 Years","language":"en"},{"value":"3 Tahun","language":"id"}],"value_id":857,"value_type":3,"children":[],"display_name":"3 Tahun"},{"multi_lang":[{"value":"5 Years","language":"en"},{"value":"5 Tahun","language":"id"}],"value_id":843,"value_type":3,"children":[],"display_name":"5 Tahun"},{"multi_lang":[{"value":"6 Months","language":"en"},{"value":"6 Bulan","language":"id"}],"value_id":810,"value_type":3,"children":[],"display_name":"6 Bulan"}],"name":"Masa Garansi"},"100370":{"value_list":[{"multi_lang":[{"value":"Supplier Warranty","language":"en"},{"value":"Garansi Supplier","language":"id"}],"value_id":2437,"value_type":3,"children":[],"display_name":"Garansi Supplier"},{"multi_lang":[{"value":"Manufacturer Warranty","language":"en"},{"value":"Garansi Produsen","language":"id"}],"value_id":2419,"value_type":3,"children":[],"display_name":"Garansi Produsen"},{"multi_lang":[{"value":"International Warranty","language":"en"},{"value":"Garansi Internasional","language":"id"}],"value_id":2397,"value_type":3,"children":[],"display_name":"Garansi Internasional"}],"name":"Jenis Garansi"},"100396":{"value_list":[],"name":"Ukuran Pelindung Hard Disk"},"100942":{"value_list":[],"name":"Dimensi (P x L x T)"},"100967":{"value_list":[],"name":"TIS No."},"100969":{"value_list":[],"name":"BSMI"},"100970":{"value_list":[],"name":"NCC"}}